MANIFEST.in
setup.py
addressformat/__init__.py
addressformat/exceptions.py
addressformat/instance.py
addressformat/project_setting.py
addressformat/structures.py
addressformat.egg-info/PKG-INFO
addressformat.egg-info/SOURCES.txt
addressformat.egg-info/dependency_links.txt
addressformat.egg-info/requires.txt
addressformat.egg-info/top_level.txt
addressformat/entitywords/city
addressformat/entitywords/county
addressformat/entitywords/ignore
addressformat/entitywords/province
addressformat/entitywords/town
addressformat/resources/__init__.py
addressformat/resources/address_dict.csv
addressformat/resources/pca.csv
addressformat/resources/sz.csv
addressformat/resources/town_dict.csv
addressformat/utils/__init__.py
addressformat/utils/tried_tree_utils.py
tests/__init__.py
tests/convert_pca.py
tests/test_cpca.py
tests/test_drawer.py
tests/test_resources.py
tests/test_structures.py